binary_matrix/2by2/02_2x2_vec_mul.v
// Time scale and resolution for simulation
`timescale 1ns / 1ps

/* In this module we define matrix vector multiplication for 2 x 2 matrices over
the scaler field of the dihedral group D_2 of order 2 (multiplication and addition mod 2)

in D_2, 
    multiplication corresponds to and
    addition corresponds to xor

 */
module matrix_vec_mul (

    // 2x2 matrix M
    input wire a,
    input wire b,
    input wire c,
    input wire d,

    input wire e,
    input wire f,

    // u
    output wire g,
    output wire h

    // u = M v
    );

    //|g| |a  b| |e|
    //| |=|    | | |
    //|h| |c  d| |f|
    assign g = (a && e) ^ (b && f);
    assign h = (c && e) ^ (d && f); 
endmodule // voter

binary_matrix/02_2x2_vec_mul_tb.v
// Simulation time scale and precision
`timescale 1ns / 1ps

module test();

    // Internal signals
    /* Signals to make connections to the UUT */
    reg a, b, c, d, e, f;    // inputs to the UUT
    wire g, h;         // output of the UUT

    matrix_vec_mul uut (.a(a), .b(b), .c(c), .d(d), .e(e), .f(f), .g(g), .h(h));

    initial begin
        // Input signal initialization
        a = 0;
        b = 0;
        c = 0;
        d = 0;
        
        e = 0;
        f = 0;

        // Waveform generation
        $dumpfile("02_2x2_vec_mul_tb.vcd");  // Waveform file
        $dumpvars(0, test);         // signals to plot (everything)

        // We finish simulation at t=100
        #320 $finish;
    end

    /* Generation of input patterns to simulate the UUT */
    // a, b and c will got through all possible combinations
    always
        #5 a = ~a;
    always
        #10 b = ~b;
    always
        #20 c = ~c;
    always
        #40 d = ~d;

    always
        #80 e = ~e;
    always
        #160 f = ~f;

endmodule // test

binary_matrix/2by2/02_2x2_vec_mul_tb.vcd
$date
	Sat May 28 12:51:25 2022
$end
$version
	Icarus Verilog
$end
$timescale
	1ps
$end
$scope module test $end
$var wire 1 ! h $end
$var wire 1 " g $end
$var reg 1 # a $end
$var reg 1 $ b $end
$var reg 1 % c $end
$var reg 1 & d $end
$var reg 1 ' e $end
$var reg 1 ( f $end
$scope module uut $end
$var wire 1 # a $end
$var wire 1 $ b $end
$var wire 1 % c $end
$var wire 1 & d $end
$var wire 1 ' e $end
$var wire 1 ( f $end
$var wire 1 " g $end
$var wire 1 ! h $end
$upscope $end
$upscope $end
$enddefinitions $end
#0
$dumpvars
0(
0'
0&
0%
0$
0#
0"
0!
$end
#5000
1#
#10000
0#
1$
#15000
1#
#20000
0#
0$
1%
#25000
1#
#30000
0#
1$
#35000
1#
#40000
0#
0$
0%
1&
#45000
1#
#50000
0#
1$
#55000
1#
#60000
0#
0$
1%
#65000
1#
#70000
0#
1$
#75000
1#
#80000
0#
0$
0%
0&
1'
#85000
1"
1#
#90000
0"
0#
1$
#95000
1"
1#
#100000
0"
1!
0#
0$
1%
#105000
1"
1#
#110000
0"
0#
1$
#115000
1"
1#
#120000
0"
0!
0#
0$
0%
1&
#125000
1"
1#
#130000
0"
0#
1$
#135000
1"
1#
#140000
0"
1!
0#
0$
1%
#145000
1"
1#
#150000
0"
0#
1$
#155000
1"
1#
#160000
0"
0!
0#
0$
0%
0&
0'
1(
#165000
1#
#170000
1"
0#
1$
#175000
1#
#180000
0"
0#
0$
1%
#185000
1#
#190000
1"
0#
1$
#195000
1#
#200000
0"
1!
0#
0$
0%
1&
#205000
1#
#210000
1"
0#
1$
#215000
1#
#220000
0"
0#
0$
1%
#225000
1#
#230000
1"
0#
1$
#235000
1#
#240000
0"
0!
0#
0$
0%
0&
1'
#245000
1"
1#
#250000
0#
1$
#255000
0"
1#
#260000
1!
0#
0$
1%
#265000
1"
1#
#270000
0#
1$
#275000
0"
1#
#280000
0#
0$
0%
1&
#285000
1"
1#
#290000
0#
1$
#295000
0"
1#
#300000
0!
0#
0$
1%
#305000
1"
1#
#310000
0#
1$
#315000
0"
1#
#320000
0#
0$
0%
0&
0'
0(
